CHANGES.txt
COPYRIGHT.txt
LICENSE.txt
README.txt
bootstrap.py
buildout.cfg
setup.py
src/zamplugin/__init__.py
src/zamplugin.contents.egg-info/PKG-INFO
src/zamplugin.contents.egg-info/SOURCES.txt
src/zamplugin.contents.egg-info/dependency_links.txt
src/zamplugin.contents.egg-info/namespace_packages.txt
src/zamplugin.contents.egg-info/not-zip-safe
src/zamplugin.contents.egg-info/requires.txt
src/zamplugin.contents.egg-info/top_level.txt
src/zamplugin/contents/README.txt
src/zamplugin/contents/__init__.py
src/zamplugin/contents/browser.zcml
src/zamplugin/contents/configure.zcml
src/zamplugin/contents/ftesting.zcml
src/zamplugin/contents/menu.py
src/zamplugin/contents/menu.zcml
src/zamplugin/contents/plugin.py
src/zamplugin/contents/plugin.zcml
src/zamplugin/contents/tests.py